{
  "dashboard": {
    "annotations": {
      "list": [
        {
          "builtIn": 1,
          "datasource": {
            "type": "prometheus",
            "uid": "${DataSource}"
          },
          "enable": true,
          "hide": true,
          "iconColor": "rgba(0, 211, 255, 1)",
          "name": "Annotations & Alerts",
          "type": "dashboard"
        }
      ]
    },
    "editable": true,
    "fiscalYearStartMonth": 0,
    "graphTooltip": 0,
    "links": [
      {
        "asDropdown": false,
        "icon": "dashboard",
        "includeVars": false,
        "keepTime": true,
        "tags": [],
        "targetBlank": false,
        "title": "Charts",
        "tooltip": "",
        "type": "link",
        "url": "/d/ebf72f09-701d-43bc-9ae3-4742b98ff98a/all-maps-columns-total-charts?${__url_time_range}"
      },
      {
        "asDropdown": false,
        "icon": "dashboard",
        "includeVars": false,
        "keepTime": true,
        "tags": [],
        "targetBlank": false,
        "title": "Main",
        "tooltip": "",
        "type": "link",
        "url": "/d/ed5d1905-d13d-446a-83d5-3d33d3aadddc/00main?var-DataSource=$DataSource&var-Cluster=$Cluster&${__url_time_range}"
      },
      {
        "asDropdown": true,
        "icon": "external link",
        "includeVars": false,
        "keepTime": true,
        "tags": [
          "gemfire"
        ],
        "targetBlank": false,
        "title": "GemFire",
        "tooltip": "",
        "type": "dashboards",
        "url": ""
      },
      {
        "asDropdown": false,
        "icon": "dashboard",
        "includeVars": false,
        "keepTime": true,
        "tags": [],
        "targetBlank": false,
        "title": "Dual Main",
        "tooltip": "",
        "type": "link",
        "url": "/d/2f6503d9-5b23-4af6-9a87-08f799229df5/00dual-main?var-DataSource=$DataSource&var-Cluster=$Cluster&var-Cluster2=$Cluster2&${__url_time_range}"
      },
      {
        "asDropdown": true,
        "icon": "external link",
        "includeVars": false,
        "keepTime": true,
        "tags": [
          "dual gemfire"
        ],
        "targetBlank": false,
        "title": "Dual GemFire",
        "tooltip": "",
        "type": "dashboards",
        "url": ""
      },
      {
        "asDropdown": false,
        "icon": "dashboard",
        "includeVars": false,
        "keepTime": true,
        "tags": [],
        "targetBlank": false,
        "title": "All Main",
        "tooltip": "",
        "type": "link",
        "url": "/d/5a076038-1d97-4c44-abe7-26020351d90b/00main-all?${__url_time_range}"
      },
      {
        "asDropdown": true,
        "icon": "external link",
        "includeVars": false,
        "keepTime": true,
        "tags": [
          "all gemfire"
        ],
        "targetBlank": false,
        "title": "All GemFire",
        "tooltip": "",
        "type": "dashboards",
        "url": ""
      },
      {
        "asDropdown": false,
        "icon": "dashboard",
        "includeVars": false,
        "keepTime": false,
        "tags": [],
        "targetBlank": false,
        "title": "Help",
        "tooltip": "PadoGrid GemFire Dashboards overview and help",
        "type": "link",
        "url": "/d/96e45270-7f77-4f87-89f3-1ab707a30808/padogrid${__url_time_range}"
      }
    ],
    "panels": [
      {
        "datasource": {
          "type": "prometheus",
          "uid": "${DataSource}"
        },
        "description": "Number of partitioned region entries owned by the member",
        "fieldConfig": {
          "defaults": {
            "color": {
              "mode": "thresholds"
            },
            "custom": {
              "align": "auto",
              "cellOptions": {
                "type": "color-text"
              },
              "inspect": false
            },
            "links": [],
            "mappings": [],
            "thresholds": {
              "mode": "absolute",
              "steps": [
                {
                  "color": "green",
                  "value": null
                }
              ]
            },
            "unit": "locale"
          },
          "overrides": [
            {
              "matcher": {
                "id": "byName",
                "options": "Member"
              },
              "properties": [
                {
                  "id": "links",
                  "value": [
                    {
                      "title": "Member Link",
                      "url": "/d/c5932a49-ac31-44d9-95fe-b3eeb7ac974f/member?orgId=1&refresh=5s&var-DataSource=$DataSource&var-Cluster=$Cluster&var-Member=${__value.text}&${__url_time_range}"
                    }
                  ]
                },
                {
                  "id": "color",
                  "value": {
                    "fixedColor": "blue",
                    "mode": "fixed"
                  }
                }
              ]
            },
            {
              "matcher": {
                "id": "byRegexp",
                "options": "\\/.*"
              },
              "properties": [
                {
                  "id": "links",
                  "value": [
                    {
                      "title": "Region Link",
                      "url": "/d/110366ca-9675-498f-bb1a-75c2273336fb/map?var-DataSource=$DataSource&var-Cluster=$Cluster&var-Map=${__field.name}&var-MapType=map&${__url_time_range}"
                    }
                  ]
                }
              ]
            }
          ]
        },
        "gridPos": {
          "h": 6,
          "w": 24,
          "x": 0,
          "y": 0
        },
        "id": 5,
        "options": {
          "cellHeight": "sm",
          "footer": {
            "countRows": false,
            "fields": "",
            "reducer": [
              "sum"
            ],
            "show": true
          },
          "showHeader": true,
          "sortBy": []
        },
        "pluginVersion": "11.3.1",
        "targets": [
          {
            "datasource": {
              "type": "prometheus",
              "uid": "${DataSource}"
            },
            "editorMode": "code",
            "exemplar": false,
            "expr": "gemfire_dataStoreEntryCount{$ClusterFilterLabel=~\"$ClusterList\",category=\"PartitionedRegionStats\"}",
            "format": "time_series",
            "instant": true,
            "legendFormat": "__auto",
            "range": false,
            "refId": "A"
          }
        ],
        "title": "Partitioned Regions: Entries",
        "transformations": [
          {
            "id": "joinByLabels",
            "options": {
              "join": [
                "instance"
              ],
              "value": "exported_instance"
            }
          },
          {
            "id": "renameByRegex",
            "options": {
              "regex": "instance",
              "renamePattern": "Member"
            }
          },
          {
            "id": "sortBy",
            "options": {
              "fields": {},
              "sort": [
                {
                  "field": "Member"
                }
              ]
            }
          }
        ],
        "type": "table"
      },
      {
        "datasource": {
          "type": "prometheus",
          "uid": "${DataSource}"
        },
        "description": "Primary value sizes in bytes per member. This does not include keys and entry overheads. ",
        "fieldConfig": {
          "defaults": {
            "color": {
              "mode": "thresholds"
            },
            "custom": {
              "align": "auto",
              "cellOptions": {
                "type": "color-text"
              },
              "inspect": false
            },
            "links": [],
            "mappings": [],
            "thresholds": {
              "mode": "absolute",
              "steps": [
                {
                  "color": "green",
                  "value": null
                }
              ]
            },
            "unit": "bytes"
          },
          "overrides": [
            {
              "matcher": {
                "id": "byName",
                "options": "Member"
              },
              "properties": [
                {
                  "id": "links",
                  "value": [
                    {
                      "title": "Member Link",
                      "url": "/d/c5932a49-ac31-44d9-95fe-b3eeb7ac974f/member?orgId=1&refresh=5s&var-DataSource=$DataSource&var-Cluster=$Cluster&var-Member=${__value.text}&${__url_time_range}"
                    }
                  ]
                },
                {
                  "id": "color",
                  "value": {
                    "fixedColor": "blue",
                    "mode": "fixed"
                  }
                }
              ]
            },
            {
              "matcher": {
                "id": "byRegexp",
                "options": "\\/.*"
              },
              "properties": [
                {
                  "id": "links",
                  "value": [
                    {
                      "title": "Region Link",
                      "url": "/d/110366ca-9675-498f-bb1a-75c2273336fb/map?var-DataSource=$DataSource&var-Cluster=$Cluster&var-Map=${__field.name}&var-MapType=map&${__url_time_range}"
                    }
                  ]
                }
              ]
            }
          ]
        },
        "gridPos": {
          "h": 6,
          "w": 24,
          "x": 0,
          "y": 6
        },
        "id": 22,
        "options": {
          "cellHeight": "sm",
          "footer": {
            "countRows": false,
            "fields": "",
            "reducer": [
              "sum"
            ],
            "show": true
          },
          "showHeader": true,
          "sortBy": []
        },
        "pluginVersion": "11.3.1",
        "targets": [
          {
            "datasource": {
              "type": "prometheus",
              "uid": "${DataSource}"
            },
            "editorMode": "code",
            "exemplar": false,
            "expr": "gemfire_dataStoreBytesInUse{$ClusterFilterLabel=~\"$ClusterList\",category=\"PartitionedRegionStats\"}",
            "format": "time_series",
            "instant": true,
            "legendFormat": "__auto",
            "range": false,
            "refId": "A"
          }
        ],
        "title": "Partitioned Regions: Primary Memory",
        "transformations": [
          {
            "id": "joinByLabels",
            "options": {
              "join": [
                "instance"
              ],
              "value": "exported_instance"
            }
          },
          {
            "id": "renameByRegex",
            "options": {
              "regex": "instance",
              "renamePattern": "Member"
            }
          },
          {
            "id": "sortBy",
            "options": {
              "fields": {},
              "sort": [
                {
                  "field": "Member"
                }
              ]
            }
          }
        ],
        "type": "table"
      },
      {
        "datasource": {
          "type": "prometheus",
          "uid": "${DataSource}"
        },
        "description": "Average object size in each member's partitioned region.",
        "fieldConfig": {
          "defaults": {
            "color": {
              "mode": "thresholds"
            },
            "custom": {
              "align": "auto",
              "cellOptions": {
                "type": "color-text"
              },
              "inspect": false
            },
            "links": [],
            "mappings": [],
            "thresholds": {
              "mode": "absolute",
              "steps": [
                {
                  "color": "green",
                  "value": null
                }
              ]
            },
            "unit": "bytes"
          },
          "overrides": [
            {
              "matcher": {
                "id": "byName",
                "options": "Member"
              },
              "properties": [
                {
                  "id": "links",
                  "value": [
                    {
                      "title": "Member Link",
                      "url": "/d/c5932a49-ac31-44d9-95fe-b3eeb7ac974f/member?orgId=1&refresh=5s&var-DataSource=$DataSource&var-Cluster=$Cluster&var-Member=${__value.text}&${__url_time_range}"
                    }
                  ]
                },
                {
                  "id": "color",
                  "value": {
                    "fixedColor": "blue",
                    "mode": "fixed"
                  }
                }
              ]
            },
            {
              "matcher": {
                "id": "byRegexp",
                "options": "\\/.*"
              },
              "properties": [
                {
                  "id": "links",
                  "value": [
                    {
                      "title": "Region Link",
                      "url": "/d/110366ca-9675-498f-bb1a-75c2273336fb/map?var-DataSource=$DataSource&var-Cluster=$Cluster&var-Map=${__field.name}&var-MapType=map&${__url_time_range}"
                    }
                  ]
                }
              ]
            }
          ]
        },
        "gridPos": {
          "h": 6,
          "w": 24,
          "x": 0,
          "y": 12
        },
        "id": 23,
        "options": {
          "cellHeight": "sm",
          "footer": {
            "countRows": false,
            "fields": "",
            "reducer": [
              "sum"
            ],
            "show": true
          },
          "showHeader": true,
          "sortBy": []
        },
        "pluginVersion": "11.3.1",
        "targets": [
          {
            "datasource": {
              "type": "prometheus",
              "uid": "${DataSource}"
            },
            "editorMode": "code",
            "exemplar": false,
            "expr": "gemfire_dataStoreBytesInUse{$ClusterFilterLabel=~\"$ClusterList\",category=\"PartitionedRegionStats\"}/gemfire_dataStoreEntryCount{$ClusterFilterLabel=~\"$ClusterList\",category=\"PartitionedRegionStats\"}",
            "format": "time_series",
            "instant": true,
            "legendFormat": "__auto",
            "range": false,
            "refId": "A"
          }
        ],
        "title": "Partitioned Regions: Average Object Size",
        "transformations": [
          {
            "id": "joinByLabels",
            "options": {
              "join": [
                "instance"
              ],
              "value": "exported_instance"
            }
          },
          {
            "id": "renameByRegex",
            "options": {
              "regex": "instance",
              "renamePattern": "Member"
            }
          },
          {
            "id": "sortBy",
            "options": {
              "fields": {},
              "sort": [
                {
                  "field": "Member"
                }
              ]
            }
          }
        ],
        "type": "table"
      },
      {
        "datasource": {
          "type": "prometheus",
          "uid": "${DataSource}"
        },
        "description": "Number of times a get on the cache did find a value already in local memory.",
        "fieldConfig": {
          "defaults": {
            "color": {
              "mode": "thresholds"
            },
            "custom": {
              "align": "auto",
              "cellOptions": {
                "type": "color-text"
              },
              "inspect": false
            },
            "links": [],
            "mappings": [],
            "thresholds": {
              "mode": "absolute",
              "steps": [
                {
                  "color": "green",
                  "value": null
                }
              ]
            },
            "unit": "locale"
          },
          "overrides": [
            {
              "matcher": {
                "id": "byRegexp",
                "options": "Member"
              },
              "properties": [
                {
                  "id": "links",
                  "value": [
                    {
                      "title": "Member Link",
                      "url": "/d/c5932a49-ac31-44d9-95fe-b3eeb7ac974f/member?orgId=1&refresh=5s&var-DataSource=$DataSource&var-Cluster=$Cluster&var-Member=${__value.text}&${__url_time_range}"
                    }
                  ]
                },
                {
                  "id": "color",
                  "value": {
                    "fixedColor": "blue",
                    "mode": "fixed"
                  }
                }
              ]
            }
          ]
        },
        "gridPos": {
          "h": 6,
          "w": 24,
          "x": 0,
          "y": 18
        },
        "id": 24,
        "options": {
          "cellHeight": "sm",
          "footer": {
            "countRows": false,
            "fields": "",
            "reducer": [
              "sum"
            ],
            "show": true
          },
          "showHeader": true,
          "sortBy": []
        },
        "pluginVersion": "11.3.1",
        "targets": [
          {
            "datasource": {
              "type": "prometheus",
              "uid": "${DataSource}"
            },
            "editorMode": "code",
            "exemplar": false,
            "expr": "gemfire_gets{$ClusterFilterLabel=~\"$ClusterList\",category=\"CachePerfStats\"} - gemfire_misses{$ClusterFilterLabel=~\"$ClusterList\",category=\"CachePerfStats\"}",
            "format": "time_series",
            "instant": true,
            "legendFormat": "__auto",
            "range": false,
            "refId": "A"
          }
        ],
        "title": "Partitioned Regions: Cache Hits",
        "transformations": [
          {
            "id": "joinByLabels",
            "options": {
              "join": [
                "instance"
              ],
              "value": "exported_instance"
            }
          },
          {
            "id": "renameByRegex",
            "options": {
              "regex": "instance",
              "renamePattern": "Member"
            }
          },
          {
            "id": "filterFieldsByName",
            "options": {
              "byVariable": false,
              "include": {
                "pattern": "Member|RegionStats-partition-.*"
              }
            }
          },
          {
            "id": "sortBy",
            "options": {
              "fields": {},
              "sort": [
                {
                  "field": "Member"
                }
              ]
            }
          },
          {
            "id": "renameByRegex",
            "options": {
              "regex": "RegionStats-partition-(.*)",
              "renamePattern": "$1"
            }
          }
        ],
        "type": "table"
      },
      {
        "datasource": {
          "type": "prometheus",
          "uid": "${DataSource}"
        },
        "description": "Number of times a get on the cache did not find a value already in local memory.",
        "fieldConfig": {
          "defaults": {
            "color": {
              "mode": "thresholds"
            },
            "custom": {
              "align": "auto",
              "cellOptions": {
                "type": "color-text"
              },
              "inspect": false
            },
            "links": [],
            "mappings": [],
            "thresholds": {
              "mode": "absolute",
              "steps": [
                {
                  "color": "green",
                  "value": null
                }
              ]
            },
            "unit": "locale"
          },
          "overrides": [
            {
              "matcher": {
                "id": "byRegexp",
                "options": "Member"
              },
              "properties": [
                {
                  "id": "links",
                  "value": [
                    {
                      "title": "Member Link",
                      "url": "/d/c5932a49-ac31-44d9-95fe-b3eeb7ac974f/member?orgId=1&refresh=5s&var-DataSource=$DataSource&var-Cluster=$Cluster&var-Member=${__value.text}&${__url_time_range}"
                    }
                  ]
                },
                {
                  "id": "color",
                  "value": {
                    "fixedColor": "blue",
                    "mode": "fixed"
                  }
                }
              ]
            }
          ]
        },
        "gridPos": {
          "h": 6,
          "w": 24,
          "x": 0,
          "y": 24
        },
        "id": 27,
        "options": {
          "cellHeight": "sm",
          "footer": {
            "countRows": false,
            "fields": "",
            "reducer": [
              "sum"
            ],
            "show": true
          },
          "showHeader": true,
          "sortBy": []
        },
        "pluginVersion": "11.3.1",
        "targets": [
          {
            "datasource": {
              "type": "prometheus",
              "uid": "${DataSource}"
            },
            "editorMode": "code",
            "exemplar": false,
            "expr": "gemfire_misses{$ClusterFilterLabel=~\"$ClusterList\",category=\"CachePerfStats\"}",
            "format": "time_series",
            "instant": true,
            "legendFormat": "__auto",
            "range": false,
            "refId": "A"
          }
        ],
        "title": "Partitioned Regions: Cache Misses",
        "transformations": [
          {
            "id": "joinByLabels",
            "options": {
              "join": [
                "instance"
              ],
              "value": "exported_instance"
            }
          },
          {
            "id": "renameByRegex",
            "options": {
              "regex": "instance",
              "renamePattern": "Member"
            }
          },
          {
            "id": "filterFieldsByName",
            "options": {
              "byVariable": false,
              "include": {
                "pattern": "Member|RegionStats-partition-.*"
              }
            }
          },
          {
            "id": "sortBy",
            "options": {
              "fields": {},
              "sort": [
                {
                  "field": "Member"
                }
              ]
            }
          },
          {
            "id": "renameByRegex",
            "options": {
              "regex": "RegionStats-partition-(.*)",
              "renamePattern": "$1"
            }
          }
        ],
        "type": "table"
      },
      {
        "datasource": {
          "type": "prometheus",
          "uid": "${DataSource}"
        },
        "description": "Number of puts performed on the region.",
        "fieldConfig": {
          "defaults": {
            "color": {
              "mode": "thresholds"
            },
            "custom": {
              "align": "auto",
              "cellOptions": {
                "type": "color-text"
              },
              "inspect": false
            },
            "links": [],
            "mappings": [],
            "thresholds": {
              "mode": "absolute",
              "steps": [
                {
                  "color": "green",
                  "value": null
                }
              ]
            },
            "unit": "locale"
          },
          "overrides": [
            {
              "matcher": {
                "id": "byRegexp",
                "options": "Member"
              },
              "properties": [
                {
                  "id": "links",
                  "value": [
                    {
                      "title": "Member Link",
                      "url": "/d/c5932a49-ac31-44d9-95fe-b3eeb7ac974f/member?orgId=1&refresh=5s&var-DataSource=$DataSource&var-Cluster=$Cluster&var-Member=${__value.text}&${__url_time_range}"
                    }
                  ]
                },
                {
                  "id": "color",
                  "value": {
                    "fixedColor": "blue",
                    "mode": "fixed"
                  }
                }
              ]
            }
          ]
        },
        "gridPos": {
          "h": 6,
          "w": 24,
          "x": 0,
          "y": 30
        },
        "id": 37,
        "options": {
          "cellHeight": "sm",
          "footer": {
            "countRows": false,
            "fields": "",
            "reducer": [
              "sum"
            ],
            "show": true
          },
          "showHeader": true,
          "sortBy": []
        },
        "pluginVersion": "11.3.1",
        "targets": [
          {
            "datasource": {
              "type": "prometheus",
              "uid": "${DataSource}"
            },
            "editorMode": "code",
            "exemplar": false,
            "expr": "gemfire_puts{$ClusterFilterLabel=~\"$ClusterList\",category=\"CachePerfStats\"}",
            "format": "time_series",
            "instant": true,
            "legendFormat": "__auto",
            "range": false,
            "refId": "A"
          }
        ],
        "title": "Partitioned Regions: Puts",
        "transformations": [
          {
            "id": "joinByLabels",
            "options": {
              "join": [
                "instance"
              ],
              "value": "exported_instance"
            }
          },
          {
            "id": "renameByRegex",
            "options": {
              "regex": "instance",
              "renamePattern": "Member"
            }
          },
          {
            "id": "filterFieldsByName",
            "options": {
              "byVariable": false,
              "include": {
                "pattern": "Member|RegionStats-partition-.*"
              }
            }
          },
          {
            "id": "sortBy",
            "options": {
              "fields": {},
              "sort": [
                {
                  "field": "Member"
                }
              ]
            }
          },
          {
            "id": "renameByRegex",
            "options": {
              "regex": "RegionStats-partition-(.*)",
              "renamePattern": "$1"
            }
          }
        ],
        "type": "table"
      },
      {
        "datasource": {
          "type": "prometheus",
          "uid": "${DataSource}"
        },
        "description": "Number of updates performed on the region.",
        "fieldConfig": {
          "defaults": {
            "color": {
              "mode": "thresholds"
            },
            "custom": {
              "align": "auto",
              "cellOptions": {
                "type": "color-text"
              },
              "inspect": false
            },
            "links": [],
            "mappings": [],
            "thresholds": {
              "mode": "absolute",
              "steps": [
                {
                  "color": "green",
                  "value": null
                }
              ]
            },
            "unit": "locale"
          },
          "overrides": [
            {
              "matcher": {
                "id": "byRegexp",
                "options": "Member"
              },
              "properties": [
                {
                  "id": "links",
                  "value": [
                    {
                      "title": "Member Link",
                      "url": "/d/c5932a49-ac31-44d9-95fe-b3eeb7ac974f/member?orgId=1&refresh=5s&var-DataSource=$DataSource&var-Cluster=$Cluster&var-Member=${__value.text}&${__url_time_range}"
                    }
                  ]
                },
                {
                  "id": "color",
                  "value": {
                    "fixedColor": "blue",
                    "mode": "fixed"
                  }
                }
              ]
            }
          ]
        },
        "gridPos": {
          "h": 6,
          "w": 24,
          "x": 0,
          "y": 36
        },
        "id": 28,
        "options": {
          "cellHeight": "sm",
          "footer": {
            "countRows": false,
            "fields": "",
            "reducer": [
              "sum"
            ],
            "show": true
          },
          "showHeader": true,
          "sortBy": []
        },
        "pluginVersion": "11.3.1",
        "targets": [
          {
            "datasource": {
              "type": "prometheus",
              "uid": "${DataSource}"
            },
            "editorMode": "code",
            "exemplar": false,
            "expr": "gemfire_updates{$ClusterFilterLabel=~\"$ClusterList\",category=\"CachePerfStats\"}",
            "format": "time_series",
            "instant": true,
            "legendFormat": "__auto",
            "range": false,
            "refId": "A"
          }
        ],
        "title": "Partitioned Regions: Cache Updates",
        "transformations": [
          {
            "id": "joinByLabels",
            "options": {
              "join": [
                "instance"
              ],
              "value": "exported_instance"
            }
          },
          {
            "id": "renameByRegex",
            "options": {
              "regex": "instance",
              "renamePattern": "Member"
            }
          },
          {
            "id": "filterFieldsByName",
            "options": {
              "byVariable": false,
              "include": {
                "pattern": "Member|RegionStats-partition-.*"
              }
            }
          },
          {
            "id": "sortBy",
            "options": {
              "fields": {},
              "sort": [
                {
                  "field": "Member"
                }
              ]
            }
          },
          {
            "id": "renameByRegex",
            "options": {
              "regex": "RegionStats-partition-(.*)",
              "renamePattern": "$1"
            }
          }
        ],
        "type": "table"
      },
      {
        "datasource": {
          "type": "prometheus",
          "uid": "${DataSource}"
        },
        "description": "Number of gets performed on the region.",
        "fieldConfig": {
          "defaults": {
            "color": {
              "mode": "thresholds"
            },
            "custom": {
              "align": "auto",
              "cellOptions": {
                "type": "color-text"
              },
              "inspect": false
            },
            "links": [],
            "mappings": [],
            "thresholds": {
              "mode": "absolute",
              "steps": [
                {
                  "color": "green",
                  "value": null
                }
              ]
            },
            "unit": "locale"
          },
          "overrides": [
            {
              "matcher": {
                "id": "byRegexp",
                "options": "Member"
              },
              "properties": [
                {
                  "id": "links",
                  "value": [
                    {
                      "title": "Member Link",
                      "url": "/d/c5932a49-ac31-44d9-95fe-b3eeb7ac974f/member?orgId=1&refresh=5s&var-DataSource=$DataSource&var-Cluster=$Cluster&var-Member=${__value.text}&${__url_time_range}"
                    }
                  ]
                },
                {
                  "id": "color",
                  "value": {
                    "fixedColor": "blue",
                    "mode": "fixed"
                  }
                }
              ]
            }
          ]
        },
        "gridPos": {
          "h": 6,
          "w": 24,
          "x": 0,
          "y": 42
        },
        "id": 36,
        "options": {
          "cellHeight": "sm",
          "footer": {
            "countRows": false,
            "fields": "",
            "reducer": [
              "sum"
            ],
            "show": true
          },
          "showHeader": true,
          "sortBy": []
        },
        "pluginVersion": "11.3.1",
        "targets": [
          {
            "datasource": {
              "type": "prometheus",
              "uid": "${DataSource}"
            },
            "editorMode": "code",
            "exemplar": false,
            "expr": "gemfire_gets{$ClusterFilterLabel=~\"$ClusterList\",category=\"CachePerfStats\"}",
            "format": "time_series",
            "instant": true,
            "legendFormat": "__auto",
            "range": false,
            "refId": "A"
          }
        ],
        "title": "Partitioned Regions: Gets",
        "transformations": [
          {
            "id": "joinByLabels",
            "options": {
              "join": [
                "instance"
              ],
              "value": "exported_instance"
            }
          },
          {
            "id": "renameByRegex",
            "options": {
              "regex": "instance",
              "renamePattern": "Member"
            }
          },
          {
            "id": "filterFieldsByName",
            "options": {
              "byVariable": false,
              "include": {
                "pattern": "Member|RegionStats-partition-.*"
              }
            }
          },
          {
            "id": "sortBy",
            "options": {
              "fields": {},
              "sort": [
                {
                  "field": "Member"
                }
              ]
            }
          },
          {
            "id": "renameByRegex",
            "options": {
              "regex": "RegionStats-partition-(.*)",
              "renamePattern": "$1"
            }
          }
        ],
        "type": "table"
      },
      {
        "datasource": {
          "type": "prometheus",
          "uid": "${DataSource}"
        },
        "description": "Number of destroys performed on the region.",
        "fieldConfig": {
          "defaults": {
            "color": {
              "mode": "thresholds"
            },
            "custom": {
              "align": "auto",
              "cellOptions": {
                "type": "color-text"
              },
              "inspect": false
            },
            "links": [],
            "mappings": [],
            "thresholds": {
              "mode": "absolute",
              "steps": [
                {
                  "color": "green"
                }
              ]
            },
            "unit": "locale"
          },
          "overrides": [
            {
              "matcher": {
                "id": "byRegexp",
                "options": "Member"
              },
              "properties": [
                {
                  "id": "links",
                  "value": [
                    {
                      "title": "Member Link",
                      "url": "/d/c5932a49-ac31-44d9-95fe-b3eeb7ac974f/member?orgId=1&refresh=5s&var-DataSource=$DataSource&var-Cluster=$Cluster&var-Member=${__value.text}&${__url_time_range}"
                    }
                  ]
                },
                {
                  "id": "color",
                  "value": {
                    "fixedColor": "blue",
                    "mode": "fixed"
                  }
                }
              ]
            }
          ]
        },
        "gridPos": {
          "h": 6,
          "w": 24,
          "x": 0,
          "y": 48
        },
        "id": 35,
        "options": {
          "cellHeight": "sm",
          "footer": {
            "countRows": false,
            "fields": "",
            "reducer": [
              "sum"
            ],
            "show": true
          },
          "showHeader": true,
          "sortBy": []
        },
        "pluginVersion": "11.3.1",
        "targets": [
          {
            "datasource": {
              "type": "prometheus",
              "uid": "${DataSource}"
            },
            "editorMode": "code",
            "exemplar": false,
            "expr": "gemfire_destroys{$ClusterFilterLabel=~\"$ClusterList\",category=\"CachePerfStats\"}",
            "format": "time_series",
            "instant": true,
            "legendFormat": "__auto",
            "range": false,
            "refId": "A"
          }
        ],
        "title": "Partitioned Regions: Destroys",
        "transformations": [
          {
            "id": "joinByLabels",
            "options": {
              "join": [
                "instance"
              ],
              "value": "exported_instance"
            }
          },
          {
            "id": "renameByRegex",
            "options": {
              "regex": "instance",
              "renamePattern": "Member"
            }
          },
          {
            "id": "filterFieldsByName",
            "options": {
              "byVariable": false,
              "include": {
                "pattern": "Member|RegionStats-partition-.*"
              }
            }
          },
          {
            "id": "sortBy",
            "options": {
              "fields": {},
              "sort": [
                {
                  "field": "Member"
                }
              ]
            }
          },
          {
            "id": "renameByRegex",
            "options": {
              "regex": "RegionStats-partition-(.*)",
              "renamePattern": "$1"
            }
          }
        ],
        "type": "table"
      },
      {
        "datasource": {
          "type": "prometheus",
          "uid": "${DataSource}"
        },
        "description": "Number of events queued.",
        "fieldConfig": {
          "defaults": {
            "color": {
              "mode": "thresholds"
            },
            "custom": {
              "align": "auto",
              "cellOptions": {
                "type": "color-text"
              },
              "inspect": false
            },
            "links": [],
            "mappings": [],
            "thresholds": {
              "mode": "absolute",
              "steps": [
                {
                  "color": "green"
                }
              ]
            },
            "unit": "locale"
          },
          "overrides": [
            {
              "matcher": {
                "id": "byRegexp",
                "options": "Member"
              },
              "properties": [
                {
                  "id": "links",
                  "value": [
                    {
                      "title": "Member Link",
                      "url": "/d/c5932a49-ac31-44d9-95fe-b3eeb7ac974f/member?orgId=1&refresh=5s&var-DataSource=$DataSource&var-Cluster=$Cluster&var-Member=${__value.text}&${__url_time_range}"
                    }
                  ]
                },
                {
                  "id": "color",
                  "value": {
                    "fixedColor": "blue",
                    "mode": "fixed"
                  }
                }
              ]
            }
          ]
        },
        "gridPos": {
          "h": 6,
          "w": 24,
          "x": 0,
          "y": 54
        },
        "id": 32,
        "options": {
          "cellHeight": "sm",
          "footer": {
            "countRows": false,
            "fields": "",
            "reducer": [
              "sum"
            ],
            "show": true
          },
          "showHeader": true,
          "sortBy": []
        },
        "pluginVersion": "11.3.1",
        "targets": [
          {
            "datasource": {
              "type": "prometheus",
              "uid": "${DataSource}"
            },
            "editorMode": "code",
            "exemplar": false,
            "expr": "gemfire_eventsQueued{$ClusterFilterLabel=~\"$ClusterList\",category=\"CachePerfStats\"}",
            "format": "time_series",
            "instant": true,
            "legendFormat": "__auto",
            "range": false,
            "refId": "A"
          }
        ],
        "title": "Partitioned Regions: Events Queued",
        "transformations": [
          {
            "id": "joinByLabels",
            "options": {
              "join": [
                "instance"
              ],
              "value": "exported_instance"
            }
          },
          {
            "id": "renameByRegex",
            "options": {
              "regex": "instance",
              "renamePattern": "Member"
            }
          },
          {
            "id": "filterFieldsByName",
            "options": {
              "byVariable": false,
              "include": {
                "pattern": "Member|RegionStats-partition-.*"
              }
            }
          },
          {
            "id": "sortBy",
            "options": {
              "fields": {},
              "sort": [
                {
                  "field": "Member"
                }
              ]
            }
          },
          {
            "id": "renameByRegex",
            "options": {
              "regex": "RegionStats-partition-(.*)",
              "renamePattern": "$1"
            }
          }
        ],
        "type": "table"
      },
      {
        "datasource": {
          "type": "prometheus",
          "uid": "${DataSource}"
        },
        "description": "Number of event threads.",
        "fieldConfig": {
          "defaults": {
            "color": {
              "mode": "thresholds"
            },
            "custom": {
              "align": "auto",
              "cellOptions": {
                "type": "color-text"
              },
              "inspect": false
            },
            "links": [],
            "mappings": [],
            "thresholds": {
              "mode": "absolute",
              "steps": [
                {
                  "color": "green"
                }
              ]
            },
            "unit": "locale"
          },
          "overrides": [
            {
              "matcher": {
                "id": "byRegexp",
                "options": "Member"
              },
              "properties": [
                {
                  "id": "links",
                  "value": [
                    {
                      "title": "Member Link",
                      "url": "/d/c5932a49-ac31-44d9-95fe-b3eeb7ac974f/member?orgId=1&refresh=5s&var-DataSource=$DataSource&var-Cluster=$Cluster&var-Member=${__value.text}&${__url_time_range}"
                    }
                  ]
                },
                {
                  "id": "color",
                  "value": {
                    "fixedColor": "blue",
                    "mode": "fixed"
                  }
                }
              ]
            }
          ]
        },
        "gridPos": {
          "h": 6,
          "w": 24,
          "x": 0,
          "y": 60
        },
        "id": 31,
        "options": {
          "cellHeight": "sm",
          "footer": {
            "countRows": false,
            "fields": "",
            "reducer": [
              "sum"
            ],
            "show": true
          },
          "showHeader": true,
          "sortBy": []
        },
        "pluginVersion": "11.3.1",
        "targets": [
          {
            "datasource": {
              "type": "prometheus",
              "uid": "${DataSource}"
            },
            "editorMode": "code",
            "exemplar": false,
            "expr": "gemfire_eventThreads{$ClusterFilterLabel=~\"$ClusterList\",category=\"CachePerfStats\"}",
            "format": "time_series",
            "instant": true,
            "legendFormat": "__auto",
            "range": false,
            "refId": "A"
          }
        ],
        "title": "Partitioned Regions: Event Threads",
        "transformations": [
          {
            "id": "joinByLabels",
            "options": {
              "join": [
                "instance"
              ],
              "value": "exported_instance"
            }
          },
          {
            "id": "renameByRegex",
            "options": {
              "regex": "instance",
              "renamePattern": "Member"
            }
          },
          {
            "id": "filterFieldsByName",
            "options": {
              "byVariable": false,
              "include": {
                "pattern": "Member|RegionStats-partition-.*"
              }
            }
          },
          {
            "id": "sortBy",
            "options": {
              "fields": {},
              "sort": [
                {
                  "field": "Member"
                }
              ]
            }
          },
          {
            "id": "renameByRegex",
            "options": {
              "regex": "RegionStats-partition-(.*)",
              "renamePattern": "$1"
            }
          }
        ],
        "type": "table"
      },
      {
        "datasource": {
          "type": "prometheus",
          "uid": "${DataSource}"
        },
        "description": "Number of evictions by criteria.",
        "fieldConfig": {
          "defaults": {
            "color": {
              "mode": "thresholds"
            },
            "custom": {
              "align": "auto",
              "cellOptions": {
                "type": "color-text"
              },
              "inspect": false
            },
            "links": [],
            "mappings": [],
            "thresholds": {
              "mode": "absolute",
              "steps": [
                {
                  "color": "green"
                }
              ]
            },
            "unit": "locale"
          },
          "overrides": [
            {
              "matcher": {
                "id": "byRegexp",
                "options": "Member"
              },
              "properties": [
                {
                  "id": "links",
                  "value": [
                    {
                      "title": "Member Link",
                      "url": "/d/c5932a49-ac31-44d9-95fe-b3eeb7ac974f/member?orgId=1&refresh=5s&var-DataSource=$DataSource&var-Cluster=$Cluster&var-Member=${__value.text}&${__url_time_range}"
                    }
                  ]
                },
                {
                  "id": "color",
                  "value": {
                    "fixedColor": "blue",
                    "mode": "fixed"
                  }
                }
              ]
            },
            {
              "matcher": {
                "id": "byName",
                "options": "lru_memory_destroy"
              },
              "properties": [
                {
                  "id": "custom.width",
                  "value": 164
                }
              ]
            },
            {
              "matcher": {
                "id": "byName",
                "options": "lru_heap_destroy"
              },
              "properties": [
                {
                  "id": "custom.width",
                  "value": 134
                }
              ]
            },
            {
              "matcher": {
                "id": "byName",
                "options": "lru_entry_overflow"
              },
              "properties": [
                {
                  "id": "custom.width",
                  "value": 174
                }
              ]
            }
          ]
        },
        "gridPos": {
          "h": 6,
          "w": 24,
          "x": 0,
          "y": 66
        },
        "id": 30,
        "options": {
          "cellHeight": "sm",
          "footer": {
            "countRows": false,
            "fields": "",
            "reducer": [
              "sum"
            ],
            "show": true
          },
          "showHeader": true,
          "sortBy": []
        },
        "pluginVersion": "11.3.1",
        "targets": [
          {
            "datasource": {
              "type": "prometheus",
              "uid": "${DataSource}"
            },
            "editorMode": "code",
            "exemplar": false,
            "expr": "gemfire_evictByCriteria_evictions{$ClusterFilterLabel=~\"$ClusterList\",category=\"CachePerfStats\"}",
            "format": "time_series",
            "instant": true,
            "legendFormat": "__auto",
            "range": false,
            "refId": "A"
          }
        ],
        "title": "Partitioned Regions: Evictions",
        "transformations": [
          {
            "id": "joinByLabels",
            "options": {
              "join": [
                "instance"
              ],
              "value": "exported_instance"
            }
          },
          {
            "id": "renameByRegex",
            "options": {
              "regex": "instance",
              "renamePattern": "Member"
            }
          },
          {
            "id": "filterFieldsByName",
            "options": {
              "byVariable": false,
              "include": {
                "pattern": "Member|RegionStats-partition-.*"
              }
            }
          },
          {
            "id": "sortBy",
            "options": {
              "fields": {},
              "sort": [
                {
                  "field": "Member"
                }
              ]
            }
          },
          {
            "id": "renameByRegex",
            "options": {
              "regex": "RegionStats-partition-(.*)",
              "renamePattern": "$1"
            }
          }
        ],
        "type": "table"
      },
      {
        "datasource": {
          "type": "prometheus",
          "uid": "${DataSource}"
        },
        "description": "Number of query executions",
        "fieldConfig": {
          "defaults": {
            "color": {
              "mode": "thresholds"
            },
            "custom": {
              "align": "auto",
              "cellOptions": {
                "type": "color-text"
              },
              "inspect": false
            },
            "links": [],
            "mappings": [],
            "thresholds": {
              "mode": "absolute",
              "steps": [
                {
                  "color": "green"
                }
              ]
            },
            "unit": "locale"
          },
          "overrides": [
            {
              "matcher": {
                "id": "byRegexp",
                "options": "Member"
              },
              "properties": [
                {
                  "id": "links",
                  "value": [
                    {
                      "title": "Member Link",
                      "url": "/d/c5932a49-ac31-44d9-95fe-b3eeb7ac974f/member?orgId=1&refresh=5s&var-DataSource=$DataSource&var-Cluster=$Cluster&var-Member=${__value.text}&${__url_time_range}"
                    }
                  ]
                },
                {
                  "id": "color",
                  "value": {
                    "fixedColor": "blue",
                    "mode": "fixed"
                  }
                }
              ]
            }
          ]
        },
        "gridPos": {
          "h": 6,
          "w": 24,
          "x": 0,
          "y": 72
        },
        "id": 29,
        "options": {
          "cellHeight": "sm",
          "footer": {
            "countRows": false,
            "fields": "",
            "reducer": [
              "sum"
            ],
            "show": true
          },
          "showHeader": true,
          "sortBy": []
        },
        "pluginVersion": "11.3.1",
        "targets": [
          {
            "datasource": {
              "type": "prometheus",
              "uid": "${DataSource}"
            },
            "editorMode": "code",
            "exemplar": false,
            "expr": "gemfire_queryExecutions{$ClusterFilterLabel=~\"$ClusterList\",category=\"CachePerfStats\"}",
            "format": "time_series",
            "instant": true,
            "legendFormat": "__auto",
            "range": false,
            "refId": "A"
          }
        ],
        "title": "Partitioned Regions: Query Executions",
        "transformations": [
          {
            "id": "joinByLabels",
            "options": {
              "join": [
                "instance"
              ],
              "value": "exported_instance"
            }
          },
          {
            "id": "renameByRegex",
            "options": {
              "regex": "instance",
              "renamePattern": "Member"
            }
          },
          {
            "id": "filterFieldsByName",
            "options": {
              "byVariable": false,
              "include": {
                "pattern": "Member|RegionStats-partition-.*"
              }
            }
          },
          {
            "id": "sortBy",
            "options": {
              "fields": {},
              "sort": [
                {
                  "field": "Member"
                }
              ]
            }
          },
          {
            "id": "renameByRegex",
            "options": {
              "regex": "RegionStats-partition-(.*)",
              "renamePattern": "$1"
            }
          }
        ],
        "type": "table"
      },
      {
        "datasource": {
          "type": "prometheus",
          "uid": "${DataSource}"
        },
        "description": "Number of transaction failures.",
        "fieldConfig": {
          "defaults": {
            "color": {
              "mode": "thresholds"
            },
            "custom": {
              "align": "auto",
              "cellOptions": {
                "type": "color-text"
              },
              "inspect": false
            },
            "links": [],
            "mappings": [],
            "thresholds": {
              "mode": "absolute",
              "steps": [
                {
                  "color": "green"
                }
              ]
            },
            "unit": "locale"
          },
          "overrides": [
            {
              "matcher": {
                "id": "byRegexp",
                "options": "Member"
              },
              "properties": [
                {
                  "id": "links",
                  "value": [
                    {
                      "title": "Member Link",
                      "url": "/d/c5932a49-ac31-44d9-95fe-b3eeb7ac974f/member?orgId=1&refresh=5s&var-DataSource=$DataSource&var-Cluster=$Cluster&var-Member=${__value.text}&${__url_time_range}"
                    }
                  ]
                },
                {
                  "id": "color",
                  "value": {
                    "fixedColor": "blue",
                    "mode": "fixed"
                  }
                }
              ]
            }
          ]
        },
        "gridPos": {
          "h": 6,
          "w": 24,
          "x": 0,
          "y": 78
        },
        "id": 33,
        "options": {
          "cellHeight": "sm",
          "footer": {
            "countRows": false,
            "fields": "",
            "reducer": [
              "sum"
            ],
            "show": true
          },
          "showHeader": true,
          "sortBy": []
        },
        "pluginVersion": "11.3.1",
        "targets": [
          {
            "datasource": {
              "type": "prometheus",
              "uid": "${DataSource}"
            },
            "editorMode": "code",
            "exemplar": false,
            "expr": "gemfire_txFailures{$ClusterFilterLabel=~\"$ClusterList\",category=\"CachePerfStats\"}",
            "format": "time_series",
            "instant": true,
            "legendFormat": "__auto",
            "range": false,
            "refId": "A"
          }
        ],
        "title": "Partitioned Regions: TX Failures",
        "transformations": [
          {
            "id": "joinByLabels",
            "options": {
              "join": [
                "instance"
              ],
              "value": "exported_instance"
            }
          },
          {
            "id": "renameByRegex",
            "options": {
              "regex": "instance",
              "renamePattern": "Member"
            }
          },
          {
            "id": "filterFieldsByName",
            "options": {
              "byVariable": false,
              "include": {
                "pattern": "Member|RegionStats-partition-.*"
              }
            }
          },
          {
            "id": "sortBy",
            "options": {
              "fields": {},
              "sort": [
                {
                  "field": "Member"
                }
              ]
            }
          },
          {
            "id": "renameByRegex",
            "options": {
              "regex": "RegionStats-partition-(.*)",
              "renamePattern": "$1"
            }
          }
        ],
        "type": "table"
      },
      {
        "datasource": {
          "type": "prometheus",
          "uid": "${DataSource}"
        },
        "description": "Number of transaction rollbacks.",
        "fieldConfig": {
          "defaults": {
            "color": {
              "mode": "thresholds"
            },
            "custom": {
              "align": "auto",
              "cellOptions": {
                "type": "color-text"
              },
              "inspect": false
            },
            "links": [],
            "mappings": [],
            "thresholds": {
              "mode": "absolute",
              "steps": [
                {
                  "color": "green"
                }
              ]
            },
            "unit": "locale"
          },
          "overrides": [
            {
              "matcher": {
                "id": "byRegexp",
                "options": "Member"
              },
              "properties": [
                {
                  "id": "links",
                  "value": [
                    {
                      "title": "Member Link",
                      "url": "/d/c5932a49-ac31-44d9-95fe-b3eeb7ac974f/member?orgId=1&refresh=5s&var-DataSource=$DataSource&var-Cluster=$Cluster&var-Member=${__value.text}&${__url_time_range}"
                    }
                  ]
                },
                {
                  "id": "color",
                  "value": {
                    "fixedColor": "blue",
                    "mode": "fixed"
                  }
                }
              ]
            }
          ]
        },
        "gridPos": {
          "h": 6,
          "w": 24,
          "x": 0,
          "y": 84
        },
        "id": 34,
        "options": {
          "cellHeight": "sm",
          "footer": {
            "countRows": false,
            "fields": "",
            "reducer": [
              "sum"
            ],
            "show": true
          },
          "showHeader": true,
          "sortBy": []
        },
        "pluginVersion": "11.3.1",
        "targets": [
          {
            "datasource": {
              "type": "prometheus",
              "uid": "${DataSource}"
            },
            "editorMode": "code",
            "exemplar": false,
            "expr": "gemfire_txRollbacks{$ClusterFilterLabel=~\"$ClusterList\",category=\"CachePerfStats\"}",
            "format": "time_series",
            "instant": true,
            "legendFormat": "__auto",
            "range": false,
            "refId": "A"
          }
        ],
        "title": "Partitioned Regions: TX Rollbacks",
        "transformations": [
          {
            "id": "joinByLabels",
            "options": {
              "join": [
                "instance"
              ],
              "value": "exported_instance"
            }
          },
          {
            "id": "renameByRegex",
            "options": {
              "regex": "instance",
              "renamePattern": "Member"
            }
          },
          {
            "id": "filterFieldsByName",
            "options": {
              "byVariable": false,
              "include": {
                "pattern": "Member|RegionStats-partition-.*"
              }
            }
          },
          {
            "id": "sortBy",
            "options": {
              "fields": {},
              "sort": [
                {
                  "field": "Member"
                }
              ]
            }
          },
          {
            "id": "renameByRegex",
            "options": {
              "regex": "RegionStats-partition-(.*)",
              "renamePattern": "$1"
            }
          }
        ],
        "type": "table"
      }
    ],
    "preload": false,
    "refresh": "5s",
    "schemaVersion": 40,
    "tags": [
      "all gemfire",
      "storage",
      "partitioned region"
    ],
    "templating": {
      "list": [
        {
          "current": {
            "text": "job",
            "value": "job"
          },
          "hide": 2,
          "name": "ClusterFilterLabel",
          "query": "job",
          "skipUrlSync": true,
          "type": "constant",
          "datasource": {
            "type": "prometheus",
            "uid": "${DataSource}"
          }
        },
        {
          "current": {
            "text": "Prometheus",
            "value": "ce54ezlklpfk0f"
          },
          "includeAll": false,
          "label": "Source",
          "name": "DataSource",
          "options": [],
          "query": "prometheus",
          "refresh": 1,
          "regex": "",
          "type": "datasource",
          "datasource": {
            "type": "prometheus",
            "uid": "${DataSource}"
          }
        },
        {
          "current": {
            "text": "wan1",
            "value": "wan1"
          },
          "datasource": {
            "type": "prometheus",
            "uid": "${DataSource}"
          },
          "definition": "label_values(gemfire_nodes{member_type=\"server\"},$ClusterFilterLabel)",
          "hide": 2,
          "includeAll": false,
          "label": "Cluster",
          "name": "Cluster",
          "options": [],
          "query": {
            "qryType": 1,
            "query": "label_values(gemfire_nodes{member_type=\"server\"},$ClusterFilterLabel)",
            "refId": "PrometheusVariableQueryEditor-VariableQuery"
          },
          "refresh": 1,
          "regex": "",
          "type": "query"
        },
        {
          "current": {
            "text": "Prometheus",
            "value": "ce54ezlklpfk0f"
          },
          "hide": 2,
          "includeAll": false,
          "label": "Source2",
          "name": "DataSource2",
          "options": [],
          "query": "prometheus",
          "refresh": 1,
          "regex": "",
          "type": "datasource",
          "datasource": {
            "type": "prometheus",
            "uid": "${DataSource}"
          }
        },
        {
          "current": {
            "text": "wan1",
            "value": "wan1"
          },
          "datasource": {
            "type": "prometheus",
            "uid": "${DataSource}"
          },
          "definition": "label_values(gemfire_nodes{member_type=\"server\"},$ClusterFilterLabel)",
          "hide": 2,
          "includeAll": false,
          "label": "Cluster2",
          "name": "Cluster2",
          "options": [],
          "query": {
            "qryType": 1,
            "query": "label_values(gemfire_nodes{member_type=\"server\"},$ClusterFilterLabel)",
            "refId": "PrometheusVariableQueryEditor-VariableQuery"
          },
          "refresh": 1,
          "regex": "",
          "type": "query"
        },
        {
          "current": {
            "text": [
              "All"
            ],
            "value": [
              "$__all"
            ]
          },
          "datasource": {
            "type": "prometheus",
            "uid": "${DataSource}"
          },
          "definition": "label_values(gemfire_nodes{member_type=\"server\"},$ClusterFilterLabel)",
          "includeAll": true,
          "label": "Clusters",
          "multi": true,
          "name": "ClusterList",
          "options": [],
          "query": {
            "qryType": 1,
            "query": "label_values(gemfire_nodes{member_type=\"server\"},$ClusterFilterLabel)",
            "refId": "PrometheusVariableQueryEditor-VariableQuery"
          },
          "refresh": 1,
          "regex": "",
          "type": "query"
        }
      ]
    },
    "time": {
      "from": "now-5m",
      "to": "now"
    },
    "timepicker": {},
    "timezone": "browser",
    "title": "All Partitioned Regions Columns Total",
    "uid": "f0c94184-7607-483a-9940-136a0164f7af",
    "weekStart": ""
  },
  "folderId": "${FOLDER_ID}",
  "overWrite": false
}
